{
  "built_at": "2026-05-24T05:18:43.448424",
  "blog_id": "go-arimotomaru",
  "site": "utsumi_shinko",
  "boat": "ありもと丸",
  "months_back": 12,
  "conf": 0.3,
  "n_entries_listed": 264,
  "n_rows": 3724,
  "entries": [
    {
      "url": "https://ameblo.jp/go-arimotomaru/entry-12967073965.html",
      "posted_at": "2026-05-23T18:40:06+09:00",
      "title": "5月23日(土)　波風ありました",
      "entry_id": "12967073965"
    },
    {
      "url": "https://ameblo.jp/go-arimotomaru/entry-12966969840.html",
      "posted_at": "2026-05-22T17:20:33+09:00",
      "title": "5月22日(金)　鳥山にナブラ‼️",
      "entry_id": "12966969840"
    },
    {
      "url": "https://ameblo.jp/go-arimotomaru/entry-12966781066.html",
      "posted_at": "2026-05-20T19:50:22+09:00",
      "title": "5月20日(水)　ワラサ！マダイ！大サバ",
      "entry_id": "12966781066"
    },
    {
      "url": "https://ameblo.jp/go-arimotomaru/entry-12966566341.html",
      "posted_at": "2026-05-18T17:49:18+09:00",
      "title": "5月18日(月)　ハマチとマダイと❗",
      "entry_id": "12966566341"
    },
    {
      "url": "https://ameblo.jp/go-arimotomaru/entry-12966453054.html",
      "posted_at": "2026-05-17T17:40:16+09:00",
      "title": "5月17日(日)　青物‼️マダイ❗",
      "entry_id": "12966453054"
    },
    {
      "url": "https://ameblo.jp/go-arimotomaru/entry-12966346473.html",
      "posted_at": "2026-05-16T17:25:54+09:00",
      "title": "トカラ列島遠征　最終日です",
      "entry_id": "12966346473"
    },
    {
      "url": "https://ameblo.jp/go-arimotomaru/entry-12966344285.html",
      "posted_at": "2026-05-16T17:02:17+09:00",
      "title": "トカラ列島遠征　2日目泳がせチーム",
      "entry_id": "12966344285"
    },
    {
      "url": "https://ameblo.jp/go-arimotomaru/entry-12966342461.html",
      "posted_at": "2026-05-16T16:42:11+09:00",
      "title": "トカラ列島遠征　ジギング編",
      "entry_id": "12966342461"
    },
    {
      "url": "https://ameblo.jp/go-arimotomaru/entry-12966340480.html",
      "posted_at": "2026-05-16T16:19:25+09:00",
      "title": "トカラ列島遠征",
      "entry_id": "12966340480"
    },
    {
      "url": "https://ameblo.jp/go-arimotomaru/entry-12966331096.html",
      "posted_at": "2026-05-16T14:26:49+09:00",
      "title": "5月16日(土)　青物もやってきた～‼️‼️",
      "entry_id": "12966331096"
    },
    {
      "url": "https://ameblo.jp/go-arimotomaru/entry-12966246524.html",
      "posted_at": "2026-05-15T17:48:27+09:00",
      "title": "5月15日(金)　厳しいなかマダイ全員キャッチ",
      "entry_id": "12966246524"
    },
    {
      "url": "https://ameblo.jp/go-arimotomaru/entry-12965832499.html",
      "posted_at": "2026-05-11T17:13:08+09:00",
      "title": "5月11日(月)　トラフグ元気でした！",
      "entry_id": "12965832499"
    },
    {
      "url": "https://ameblo.jp/go-arimotomaru/entry-12965723128.html",
      "posted_at": "2026-05-10T16:56:30+09:00",
      "title": "5月10日(日)　今日はいろいろと～‼️",
      "entry_id": "12965723128"
    },
    {
      "url": "https://ameblo.jp/go-arimotomaru/entry-12965519275.html",
      "posted_at": "2026-05-08T17:54:15+09:00",
      "title": "5月8日(金)　タイラバ絶好調です‼️",
      "entry_id": "12965519275"
    },
    {
      "url": "https://ameblo.jp/go-arimotomaru/entry-12965392845.html",
      "posted_at": "2026-05-07T13:53:47+09:00",
      "title": "5月7日(木)　マダイ好調でした⤴️",
      "entry_id": "12965392845"
    },
    {
      "url": "https://ameblo.jp/go-arimotomaru/entry-12965305924.html",
      "posted_at": "2026-05-06T17:57:54+09:00",
      "title": "5月6日(水)　GW最終日でした‼️",
      "entry_id": "12965305924"
    },
    {
      "url": "https://ameblo.jp/go-arimotomaru/entry-12965173593.html",
      "posted_at": "2026-05-05T13:41:42+09:00",
      "title": "5月5日(火)　今日もタイラバマダイ好調です",
      "entry_id": "12965173593"
    },
    {
      "url": "https://ameblo.jp/go-arimotomaru/entry-12964971268.html",
      "posted_at": "2026-05-03T15:30:25+09:00",
      "title": "5月4日(日)　タイラバ好調でした～‼️",
      "entry_id": "12964971268"
    },
    {
      "url": "https://ameblo.jp/go-arimotomaru/entry-12964879694.html",
      "posted_at": "2026-05-02T17:58:50+09:00",
      "title": "5月2日(土)　今日もボチボチいい感じです⤴️",
      "entry_id": "12964879694"
    },
    {
      "url": "https://ameblo.jp/go-arimotomaru/entry-12964655050.html",
      "posted_at": "2026-04-30T17:16:41+09:00",
      "title": "4月30日(木)　今日もボチボチな感じかな",
      "entry_id": "12964655050"
    },
    {
      "url": "https://ameblo.jp/go-arimotomaru/entry-12964556262.html",
      "posted_at": "2026-04-29T18:40:25+09:00",
      "title": "4月29日(火)　良くなって来ました‼️",
      "entry_id": "12964556262"
    },
    {
      "url": "https://ameblo.jp/go-arimotomaru/entry-12964452482.html",
      "posted_at": "2026-04-28T18:31:04+09:00",
      "title": "4月28日(火)　マダイ元気～‼️",
      "entry_id": "12964452482"
    },
    {
      "url": "https://ameblo.jp/go-arimotomaru/entry-12964327288.html",
      "posted_at": "2026-04-27T14:37:17+09:00",
      "title": "4月27日(月)　ワラサ！サゴシ！トラフグ⤴️",
      "entry_id": "12964327288"
    },
    {
      "url": "https://ameblo.jp/go-arimotomaru/entry-12964218103.html",
      "posted_at": "2026-04-26T14:44:11+09:00",
      "title": "4月26日(日)　今日もトラフグ活性‼️",
      "entry_id": "12964218103"
    },
    {
      "url": "https://ameblo.jp/go-arimotomaru/entry-12964110949.html",
      "posted_at": "2026-04-25T14:29:27+09:00",
      "title": "4月Aj日(土)　トラフグ元気‼️反応増えてきましたね！",
      "entry_id": "12964110949"
    },
    {
      "url": "https://ameblo.jp/go-arimotomaru/entry-12963829324.html",
      "posted_at": "2026-04-22T18:40:35+09:00",
      "title": "4月22日(水)　マダイ‼️ハマチも釣りたかった(笑)",
      "entry_id": "12963829324"
    },
    {
      "url": "https://ameblo.jp/go-arimotomaru/entry-12963512944.html",
      "posted_at": "2026-04-19T17:50:55+09:00",
      "title": "4月19日(日)　大アジにマダイに‼️‼️",
      "entry_id": "12963512944"
    },
    {
      "url": "https://ameblo.jp/go-arimotomaru/entry-12963391864.html",
      "posted_at": "2026-04-18T14:56:59+09:00",
      "title": "4月18日(土) 今日もタイラバマダイ‼️",
      "entry_id": "12963391864"
    },
    {
      "url": "https://ameblo.jp/go-arimotomaru/entry-12963289713.html",
      "posted_at": "2026-04-17T15:08:55+09:00",
      "title": "4月17日(金)　マダイ全員キャッチ‼️",
      "entry_id": "12963289713"
    },
    {
      "url": "https://ameblo.jp/go-arimotomaru/entry-12962997071.html",
      "posted_at": "2026-04-14T17:41:10+09:00",
      "title": "4月14日(火)　後半になんとか‼️",
      "entry_id": "12962997071"
    },
    {
      "url": "https://ameblo.jp/go-arimotomaru/entry-12962877104.html",
      "posted_at": "2026-04-13T14:12:42+09:00",
      "title": "4月13日(月)　ワラサは釣れましたが…",
      "entry_id": "12962877104"
    },
    {
      "url": "https://ameblo.jp/go-arimotomaru/entry-12962780111.html",
      "posted_at": "2026-04-12T16:15:07+09:00",
      "title": "4月12日(日)　ハマチ爆釣でした～‼️",
      "entry_id": "12962780111"
    },
    {
      "url": "https://ameblo.jp/go-arimotomaru/entry-12962666891.html",
      "posted_at": "2026-04-11T14:37:40+09:00",
      "title": "4月11日(土)　海の様子が変わって来ましたよ～",
      "entry_id": "12962666891"
    },
    {
      "url": "https://ameblo.jp/go-arimotomaru/entry-12962482887.html",
      "posted_at": "2026-04-09T18:27:48+09:00",
      "title": "4月9日(木)　20年ぶりに遊びに来ていただき感謝！",
      "entry_id": "12962482887"
    },
    {
      "url": "https://ameblo.jp/go-arimotomaru/entry-12962253426.html",
      "posted_at": "2026-04-07T14:02:48+09:00",
      "title": "4月7日(火)　タイラバとジギングで！",
      "entry_id": "12962253426"
    },
    {
      "url": "https://ameblo.jp/go-arimotomaru/entry-12962150573.html",
      "posted_at": "2026-04-06T14:26:12+09:00",
      "title": "4月6日(月)　今日はいい感じでした",
      "entry_id": "12962150573"
    },
    {
      "url": "https://ameblo.jp/go-arimotomaru/entry-12962057627.html",
      "posted_at": "2026-04-05T17:30:33+09:00",
      "title": "4月5日(日)　魚おるけど難しかった！",
      "entry_id": "12962057627"
    },
    {
      "url": "https://ameblo.jp/go-arimotomaru/entry-12961842695.html",
      "posted_at": "2026-04-03T16:56:15+09:00",
      "title": "4月3日(金)　４月になりましたね",
      "entry_id": "12961842695"
    },
    {
      "url": "https://ameblo.jp/go-arimotomaru/entry-12961404679.html",
      "posted_at": "2026-03-30T17:41:18+09:00",
      "title": "3月30日(月)　サワラにマダイ‼️",
      "entry_id": "12961404679"
    },
    {
      "url": "https://ameblo.jp/go-arimotomaru/entry-12961290946.html",
      "posted_at": "2026-03-29T17:03:50+09:00",
      "title": "3月29日(日)　今日もベイト盛りだくさん",
      "entry_id": "12961290946"
    },
    {
      "url": "https://ameblo.jp/go-arimotomaru/entry-12961177950.html",
      "posted_at": "2026-03-28T16:41:30+09:00",
      "title": "3月28日(土)　ベイト大量入荷！海が変わってきた！",
      "entry_id": "12961177950"
    },
    {
      "url": "https://ameblo.jp/go-arimotomaru/entry-12961085427.html",
      "posted_at": "2026-03-27T18:20:39+09:00",
      "title": "3月27日(金)　ベイト大量入荷です",
      "entry_id": "12961085427"
    },
    {
      "url": "https://ameblo.jp/go-arimotomaru/entry-12960777821.html",
      "posted_at": "2026-03-24T18:32:00+09:00",
      "title": "3月24日(火)　軽めのジグあったほうがいいかも",
      "entry_id": "12960777821"
    },
    {
      "url": "https://ameblo.jp/go-arimotomaru/entry-12960659981.html",
      "posted_at": "2026-03-23T16:22:29+09:00",
      "title": "3月23日(月)　いい感じでした～❗",
      "entry_id": "12960659981"
    },
    {
      "url": "https://ameblo.jp/go-arimotomaru/entry-12960562591.html",
      "posted_at": "2026-03-22T17:52:13+09:00",
      "title": "3月22日(日)　サワラにワラサも顔を見せました",
      "entry_id": "12960562591"
    },
    {
      "url": "https://ameblo.jp/go-arimotomaru/entry-12960530528.html",
      "posted_at": "2026-03-22T12:11:56+09:00",
      "title": "3月21日(土)　ハマチでした‼️",
      "entry_id": "12960530528"
    },
    {
      "url": "https://ameblo.jp/go-arimotomaru/entry-12960343555.html",
      "posted_at": "2026-03-20T16:47:21+09:00",
      "title": "3月20日(金)　今日は少し難しい‼️",
      "entry_id": "12960343555"
    },
    {
      "url": "https://ameblo.jp/go-arimotomaru/entry-12960142113.html",
      "posted_at": "2026-03-18T17:38:04+09:00",
      "title": "3月18日(水)　今日も大ダイです‼️",
      "entry_id": "12960142113"
    },
    {
      "url": "https://ameblo.jp/go-arimotomaru/entry-12960024176.html",
      "posted_at": "2026-03-17T15:17:04+09:00",
      "title": "3月17日(火)　今日も春の大ダイ‼️",
      "entry_id": "12960024176"
    },
    {
      "url": "https://ameblo.jp/go-arimotomaru/entry-12959929519.html",
      "posted_at": "2026-03-16T17:12:43+09:00",
      "title": "3月16日(月)　今日もなんとか‼️",
      "entry_id": "12959929519"
    },
    {
      "url": "https://ameblo.jp/go-arimotomaru/entry-12959813251.html",
      "posted_at": "2026-03-15T15:58:39+09:00",
      "title": "3月15日(日)　大ダイです‼️",
      "entry_id": "12959813251"
    },
    {
      "url": "https://ameblo.jp/go-arimotomaru/entry-12959711395.html",
      "posted_at": "2026-03-14T16:55:47+09:00",
      "title": "3月14日(土)　ホワイトデーです❗",
      "entry_id": "12959711395"
    },
    {
      "url": "https://ameblo.jp/go-arimotomaru/entry-12959392163.html",
      "posted_at": "2026-03-11T14:42:21+09:00",
      "title": "3月11日(水)　マダイ食いました❗",
      "entry_id": "12959392163"
    },
    {
      "url": "https://ameblo.jp/go-arimotomaru/entry-12959198959.html",
      "posted_at": "2026-03-09T18:33:38+09:00",
      "title": "3月9日(月)　また休み明けです",
      "entry_id": "12959198959"
    },
    {
      "url": "https://ameblo.jp/go-arimotomaru/entry-12958846727.html",
      "posted_at": "2026-03-06T15:30:39+09:00",
      "title": "3月6日(金)　久しぶり出船‼️",
      "entry_id": "12958846727"
    },
    {
      "url": "https://ameblo.jp/go-arimotomaru/entry-12958474529.html",
      "posted_at": "2026-03-03T06:35:59+09:00",
      "title": "3月2日(月)　ハマチとマダイと～",
      "entry_id": "12958474529"
    },
    {
      "url": "https://ameblo.jp/go-arimotomaru/entry-12958289565.html",
      "posted_at": "2026-03-01T14:54:53+09:00",
      "title": "3月1日(日)　３月です‼️ハマチです‼️",
      "entry_id": "12958289565"
    },
    {
      "url": "https://ameblo.jp/go-arimotomaru/entry-12958081506.html",
      "posted_at": "2026-02-27T17:31:41+09:00",
      "title": "2月27日(金)　のんびりタイラバ",
      "entry_id": "12958081506"
    },
    {
      "url": "https://ameblo.jp/go-arimotomaru/entry-12957867679.html",
      "posted_at": "2026-02-25T16:33:58+09:00",
      "title": "2月25日(水)　雨の中行って来ました",
      "entry_id": "12957867679"
    },
    {
      "url": "https://ameblo.jp/go-arimotomaru/entry-12957766884.html",
      "posted_at": "2026-02-24T17:14:33+09:00",
      "title": "2月24日(火)　なんかいろいろ良く釣れました",
      "entry_id": "12957766884"
    },
    {
      "url": "https://ameblo.jp/go-arimotomaru/entry-12957659694.html",
      "posted_at": "2026-02-23T17:06:56+09:00",
      "title": "2月23日(月)　今日は青物残念でした",
      "entry_id": "12957659694"
    },
    {
      "url": "https://ameblo.jp/go-arimotomaru/entry-12957527413.html",
      "posted_at": "2026-02-22T14:13:23+09:00",
      "title": "2月22日(日)　222です‼️",
      "entry_id": "12957527413"
    },
    {
      "url": "https://ameblo.jp/go-arimotomaru/entry-12957440719.html",
      "posted_at": "2026-02-21T17:46:50+09:00",
      "title": "2月21日(土)　今日も青物ゲットです‼️",
      "entry_id": "12957440719"
    },
    {
      "url": "https://ameblo.jp/go-arimotomaru/entry-12957342219.html",
      "posted_at": "2026-02-20T18:13:35+09:00",
      "title": "2月20日(金)　久しぶりにブリです‼️",
      "entry_id": "12957342219"
    },
    {
      "url": "https://ameblo.jp/go-arimotomaru/entry-12957142111.html",
      "posted_at": "2026-02-18T18:41:22+09:00",
      "title": "2月18日(水)　「気まぐれクック」×「タケヤキ翔」",
      "entry_id": "12957142111"
    },
    {
      "url": "https://ameblo.jp/go-arimotomaru/entry-12956827958.html",
      "posted_at": "2026-02-15T18:46:00+09:00",
      "title": "2月15日(日)　とんでもないヤツがヒット(笑)",
      "entry_id": "12956827958"
    },
    {
      "url": "https://ameblo.jp/go-arimotomaru/entry-12956705375.html",
      "posted_at": "2026-02-14T17:15:09+09:00",
      "title": "2月14日(土)　バレンタインデー",
      "entry_id": "12956705375"
    },
    {
      "url": "https://ameblo.jp/go-arimotomaru/entry-12956598282.html",
      "posted_at": "2026-02-13T16:45:18+09:00",
      "title": "2月13日(金)　今日もホウボウ祭り",
      "entry_id": "12956598282"
    },
    {
      "url": "https://ameblo.jp/go-arimotomaru/entry-12956485056.html",
      "posted_at": "2026-02-12T14:40:07+09:00",
      "title": "2月12日(木)　ホウボウ祭り",
      "entry_id": "12956485056"
    },
    {
      "url": "https://ameblo.jp/go-arimotomaru/entry-12956334027.html",
      "posted_at": "2026-02-11T05:17:27+09:00",
      "title": "2月10日(火)　そろそろタイラバも❗",
      "entry_id": "12956334027"
    },
    {
      "url": "https://ameblo.jp/go-arimotomaru/entry-12955956227.html",
      "posted_at": "2026-02-07T17:23:09+09:00",
      "title": "2月7日(土)　久しぶりにブリ釣れた",
      "entry_id": "12955956227"
    },
    {
      "url": "https://ameblo.jp/go-arimotomaru/entry-12955849446.html",
      "posted_at": "2026-02-06T17:35:57+09:00",
      "title": "2月6日(金)　今日も難しい‼️",
      "entry_id": "12955849446"
    },
    {
      "url": "https://ameblo.jp/go-arimotomaru/entry-12955642055.html",
      "posted_at": "2026-02-04T17:49:55+09:00",
      "title": "２月４日(水)　今日はダメでした",
      "entry_id": "12955642055"
    },
    {
      "url": "https://ameblo.jp/go-arimotomaru/entry-12955426996.html",
      "posted_at": "2026-02-02T18:00:47+09:00",
      "title": "２月２日(月)　デカいシーバス‼️",
      "entry_id": "12955426996"
    },
    {
      "url": "https://ameblo.jp/go-arimotomaru/entry-12955302310.html",
      "posted_at": "2026-02-01T16:28:56+09:00",
      "title": "２月１日(日)　ホウボウ元気‼️",
      "entry_id": "12955302310"
    },
    {
      "url": "https://ameblo.jp/go-arimotomaru/entry-12955187815.html",
      "posted_at": "2026-01-31T16:32:29+09:00",
      "title": "1月31日(土)　ホウボウは元気",
      "entry_id": "12955187815"
    },
    {
      "url": "https://ameblo.jp/go-arimotomaru/entry-12955089198.html",
      "posted_at": "2026-01-30T17:24:00+09:00",
      "title": "1月30日(金) 　青物はダメでしたが",
      "entry_id": "12955089198"
    },
    {
      "url": "https://ameblo.jp/go-arimotomaru/entry-12954979363.html",
      "posted_at": "2026-01-29T16:12:50+09:00",
      "title": "1月29日(木)　今日はダメでした",
      "entry_id": "12954979363"
    },
    {
      "url": "https://ameblo.jp/go-arimotomaru/entry-12954872455.html",
      "posted_at": "2026-01-28T15:33:08+09:00",
      "title": "1月28日(水)　今日もブリがデカい❗",
      "entry_id": "12954872455"
    },
    {
      "url": "https://ameblo.jp/go-arimotomaru/entry-12954764530.html",
      "posted_at": "2026-01-27T14:46:32+09:00",
      "title": "1月27日(火)　今日もボコボコでした～‼️",
      "entry_id": "12954764530"
    },
    {
      "url": "https://ameblo.jp/go-arimotomaru/entry-12954655767.html",
      "posted_at": "2026-01-26T13:53:32+09:00",
      "title": "1月26日(月)　今日もボコボコ‼️",
      "entry_id": "12954655767"
    },
    {
      "url": "https://ameblo.jp/go-arimotomaru/entry-12954448723.html",
      "posted_at": "2026-01-24T15:22:07+09:00",
      "title": "1月24日(土)　ブリワラサボコボコでした‼️",
      "entry_id": "12954448723"
    },
    {
      "url": "https://ameblo.jp/go-arimotomaru/entry-12953942523.html",
      "posted_at": "2026-01-19T17:19:35+09:00",
      "title": "1月19日(月)　いい凪でした‼️",
      "entry_id": "12953942523"
    },
    {
      "url": "https://ameblo.jp/go-arimotomaru/entry-12953838030.html",
      "posted_at": "2026-01-18T18:07:48+09:00",
      "title": "1月18日(日)　ワラサとサワラ～‼️",
      "entry_id": "12953838030"
    },
    {
      "url": "https://ameblo.jp/go-arimotomaru/entry-12953723435.html",
      "posted_at": "2026-01-17T17:20:50+09:00",
      "title": "1月17日(土)　サワラ太いけど～",
      "entry_id": "12953723435"
    },
    {
      "url": "https://ameblo.jp/go-arimotomaru/entry-12953619994.html",
      "posted_at": "2026-01-16T17:41:58+09:00",
      "title": "1月16日(金)　ブリがデカい～‼️",
      "entry_id": "12953619994"
    },
    {
      "url": "https://ameblo.jp/go-arimotomaru/entry-12953299420.html",
      "posted_at": "2026-01-13T17:14:50+09:00",
      "title": "1月13日(火)　良く釣れました～‼️‼️",
      "entry_id": "12953299420"
    },
    {
      "url": "https://ameblo.jp/go-arimotomaru/entry-12952974378.html",
      "posted_at": "2026-01-10T18:25:33+09:00",
      "title": "1月10日(土)　いい天気でした‼️",
      "entry_id": "12952974378"
    },
    {
      "url": "https://ameblo.jp/go-arimotomaru/entry-12952864769.html",
      "posted_at": "2026-01-09T17:12:41+09:00",
      "title": "2025年‼️伊勢湾ジギングバトル結果発表‼️",
      "entry_id": "12952864769"
    },
    {
      "url": "https://ameblo.jp/go-arimotomaru/entry-12952863400.html",
      "posted_at": "2026-01-09T16:57:41+09:00",
      "title": "1月9日(金)　ワラサ少し元気あり❗",
      "entry_id": "12952863400"
    },
    {
      "url": "https://ameblo.jp/go-arimotomaru/entry-12952649407.html",
      "posted_at": "2026-01-07T16:37:22+09:00",
      "title": "1月7日(水)　なんとかブリゲットでした‼️",
      "entry_id": "12952649407"
    },
    {
      "url": "https://ameblo.jp/go-arimotomaru/entry-12952443258.html",
      "posted_at": "2026-01-05T17:37:40+09:00",
      "title": "1月5日(月)　ホウボウ！マダイ！ブリ！",
      "entry_id": "12952443258"
    },
    {
      "url": "https://ameblo.jp/go-arimotomaru/entry-12952322757.html",
      "posted_at": "2026-01-04T16:20:27+09:00",
      "title": "1月4日(日)　初出船です‼️",
      "entry_id": "12952322757"
    },
    {
      "url": "https://ameblo.jp/go-arimotomaru/entry-12951868723.html",
      "posted_at": "2025-12-31T16:04:39+09:00",
      "title": "12月31日　今年も１年ありがとうございました‼️",
      "entry_id": "12951868723"
    },
    {
      "url": "https://ameblo.jp/go-arimotomaru/entry-12951754084.html",
      "posted_at": "2025-12-30T16:44:01+09:00",
      "title": "12月30日(火)　なんとかエントリーブリ‼️",
      "entry_id": "12951754084"
    },
    {
      "url": "https://ameblo.jp/go-arimotomaru/entry-12951645553.html",
      "posted_at": "2025-12-29T16:23:45+09:00",
      "title": "12月28日29日　ブリ10キロオーバー❗",
      "entry_id": "12951645553"
    },
    {
      "url": "https://ameblo.jp/go-arimotomaru/entry-12951540437.html",
      "posted_at": "2025-12-28T16:27:23+09:00",
      "title": "12月27日(土)　ワラサボチボチでした‼️",
      "entry_id": "12951540437"
    },
    {
      "url": "https://ameblo.jp/go-arimotomaru/entry-12951283757.html",
      "posted_at": "2025-12-26T07:07:51+09:00",
      "title": "12月25日(木)　なんとかブリゲットでしたが…",
      "entry_id": "12951283757"
    },
    {
      "url": "https://ameblo.jp/go-arimotomaru/entry-12951117700.html",
      "posted_at": "2025-12-24T16:38:17+09:00",
      "title": "12月24日(水)　クリスマスイブですね",
      "entry_id": "12951117700"
    },
    {
      "url": "https://ameblo.jp/go-arimotomaru/entry-12951005257.html",
      "posted_at": "2025-12-23T15:48:02+09:00",
      "title": "12月23日(火)　今日もブリの強烈時合い‼️",
      "entry_id": "12951005257"
    },
    {
      "url": "https://ameblo.jp/go-arimotomaru/entry-12950794927.html",
      "posted_at": "2025-12-21T16:11:26+09:00",
      "title": "12月21日(日)　デカいブリボコボコ時合いあり‼️",
      "entry_id": "12950794927"
    },
    {
      "url": "https://ameblo.jp/go-arimotomaru/entry-12950699573.html",
      "posted_at": "2025-12-20T18:27:25+09:00",
      "title": "12月20日(土)　雰囲気良くなってきました❗",
      "entry_id": "12950699573"
    },
    {
      "url": "https://ameblo.jp/go-arimotomaru/entry-12950600583.html",
      "posted_at": "2025-12-19T19:28:36+09:00",
      "title": "12月19日(金)　エントリーブリ❗",
      "entry_id": "12950600583"
    },
    {
      "url": "https://ameblo.jp/go-arimotomaru/entry-12950381242.html",
      "posted_at": "2025-12-17T17:09:58+09:00",
      "title": "12月17日(水)　伸び悩みな１日でした",
      "entry_id": "12950381242"
    },
    {
      "url": "https://ameblo.jp/go-arimotomaru/entry-12950277427.html",
      "posted_at": "2025-12-16T17:23:39+09:00",
      "title": "12月16日(火)　ワラサ❗好調です‼️",
      "entry_id": "12950277427"
    },
    {
      "url": "https://ameblo.jp/go-arimotomaru/entry-12949954779.html",
      "posted_at": "2025-12-13T17:46:01+09:00",
      "title": "12月13日(土)　青物絶好調です‼️",
      "entry_id": "12949954779"
    },
    {
      "url": "https://ameblo.jp/go-arimotomaru/entry-12949745698.html",
      "posted_at": "2025-12-11T17:48:34+09:00",
      "title": "12月11日(木)　青物良くなってきましたよ❗",
      "entry_id": "12949745698"
    },
    {
      "url": "https://ameblo.jp/go-arimotomaru/entry-12949634310.html",
      "posted_at": "2025-12-10T14:16:55+09:00",
      "title": "12月10日(水)　ブリにワラサにサワラでした❗",
      "entry_id": "12949634310"
    },
    {
      "url": "https://ameblo.jp/go-arimotomaru/entry-12949530426.html",
      "posted_at": "2025-12-09T17:42:21+09:00",
      "title": "12月9日(火) 　今日は食いませんでした！",
      "entry_id": "12949530426"
    },
    {
      "url": "https://ameblo.jp/go-arimotomaru/entry-12949406431.html",
      "posted_at": "2025-12-08T14:59:03+09:00",
      "title": "12月8日(月)　ブリがデカい‼️",
      "entry_id": "12949406431"
    },
    {
      "url": "https://ameblo.jp/go-arimotomaru/entry-12949315571.html",
      "posted_at": "2025-12-07T18:25:28+09:00",
      "title": "12月7日(日)　チャーター便でした～‼️",
      "entry_id": "12949315571"
    },
    {
      "url": "https://ameblo.jp/go-arimotomaru/entry-12949202101.html",
      "posted_at": "2025-12-06T17:38:17+09:00",
      "title": "12月6日(土)　ブリ❗ワラサ❗ハマチもね‼️",
      "entry_id": "12949202101"
    },
    {
      "url": "https://ameblo.jp/go-arimotomaru/entry-12949090944.html",
      "posted_at": "2025-12-05T17:09:36+09:00",
      "title": "12月5日(金)　ジギングバトルエントリーブリでましたが…",
      "entry_id": "12949090944"
    },
    {
      "url": "https://ameblo.jp/go-arimotomaru/entry-12948766428.html",
      "posted_at": "2025-12-02T17:48:51+09:00",
      "title": "12月２日(火)　今日もなんとかでした！",
      "entry_id": "12948766428"
    },
    {
      "url": "https://ameblo.jp/go-arimotomaru/entry-12948649052.html",
      "posted_at": "2025-12-01T17:12:39+09:00",
      "title": "12月1日(月)　12月になりました❗",
      "entry_id": "12948649052"
    },
    {
      "url": "https://ameblo.jp/go-arimotomaru/entry-12948532417.html",
      "posted_at": "2025-11-30T17:19:21+09:00",
      "title": "11月30日(日)　今日は激シブ‼️",
      "entry_id": "12948532417"
    },
    {
      "url": "https://ameblo.jp/go-arimotomaru/entry-12948429472.html",
      "posted_at": "2025-11-29T18:52:42+09:00",
      "title": "11月29日(土)　難しい感じでした",
      "entry_id": "12948429472"
    },
    {
      "url": "https://ameblo.jp/go-arimotomaru/entry-12948210813.html",
      "posted_at": "2025-11-27T17:38:52+09:00",
      "title": "11月27日(木)　ワラサ！ハマチ！マダイ！",
      "entry_id": "12948210813"
    },
    {
      "url": "https://ameblo.jp/go-arimotomaru/entry-12947995624.html",
      "posted_at": "2025-11-25T17:17:03+09:00",
      "title": "11月25日(火)　今日は良く釣れました～‼️‼️",
      "entry_id": "12947995624"
    },
    {
      "url": "https://ameblo.jp/go-arimotomaru/entry-12947885818.html",
      "posted_at": "2025-11-24T17:29:22+09:00",
      "title": "11月24日(月)　ハマチはポツポツしました‼️",
      "entry_id": "12947885818"
    },
    {
      "url": "https://ameblo.jp/go-arimotomaru/entry-12947774941.html",
      "posted_at": "2025-11-23T17:23:09+09:00",
      "title": "11月23日(日)　今日はなんとかかんとかでした‼️",
      "entry_id": "12947774941"
    },
    {
      "url": "https://ameblo.jp/go-arimotomaru/entry-12947651902.html",
      "posted_at": "2025-11-22T16:38:45+09:00",
      "title": "11月22日(土)　今日は苦戦でした",
      "entry_id": "12947651902"
    },
    {
      "url": "https://ameblo.jp/go-arimotomaru/entry-12947541914.html",
      "posted_at": "2025-11-21T15:37:39+09:00",
      "title": "11月21日(金)　今日もとりあえずワラサ‼️",
      "entry_id": "12947541914"
    },
    {
      "url": "https://ameblo.jp/go-arimotomaru/entry-12947541604.html",
      "posted_at": "2025-11-21T15:34:02+09:00",
      "title": "11月19日(水)　とりあえずワラサですね‼️",
      "entry_id": "12947541604"
    },
    {
      "url": "https://ameblo.jp/go-arimotomaru/entry-12946464937.html",
      "posted_at": "2025-11-17T15:24:47+09:00",
      "title": "11月17日(月)　今日は残念‼️",
      "entry_id": "12946464937"
    },
    {
      "url": "https://ameblo.jp/go-arimotomaru/entry-12946207223.html",
      "posted_at": "2025-11-16T17:18:21+09:00",
      "title": "11月16日(日)　海遊丸たかおの追悼チャーター便でした‼️",
      "entry_id": "12946207223"
    },
    {
      "url": "https://ameblo.jp/go-arimotomaru/entry-12945915463.html",
      "posted_at": "2025-11-15T16:23:29+09:00",
      "title": "11月15日(土)　今日も大型青物～❗",
      "entry_id": "12945915463"
    },
    {
      "url": "https://ameblo.jp/go-arimotomaru/entry-12945701270.html",
      "posted_at": "2025-11-14T17:32:02+09:00",
      "title": "11月14日(金)　大型青物好調です‼️",
      "entry_id": "12945701270"
    },
    {
      "url": "https://ameblo.jp/go-arimotomaru/entry-12945353669.html",
      "posted_at": "2025-11-13T16:56:08+09:00",
      "title": "11月13日(木)　エントリーブリも釣れました‼️",
      "entry_id": "12945353669"
    },
    {
      "url": "https://ameblo.jp/go-arimotomaru/entry-12945079620.html",
      "posted_at": "2025-11-12T14:38:07+09:00",
      "title": "11月12日(水)　ケーズデンキ様の山田さんのチャーター便でした‼️",
      "entry_id": "12945079620"
    },
    {
      "url": "https://ameblo.jp/go-arimotomaru/entry-12944871945.html",
      "posted_at": "2025-11-11T17:23:55+09:00",
      "title": "11月11日(火)　今日も大型青物です⤴️",
      "entry_id": "12944871945"
    },
    {
      "url": "https://ameblo.jp/go-arimotomaru/entry-12944225776.html",
      "posted_at": "2025-11-09T15:05:49+09:00",
      "title": "11月9日(日)　雨の中頑張っていただきました‼️",
      "entry_id": "12944225776"
    },
    {
      "url": "https://ameblo.jp/go-arimotomaru/entry-12944048314.html",
      "posted_at": "2025-11-08T17:00:29+09:00",
      "title": "11月8日(土)　青物好調～‼️‼️",
      "entry_id": "12944048314"
    },
    {
      "url": "https://ameblo.jp/go-arimotomaru/entry-12943909558.html",
      "posted_at": "2025-11-07T17:23:03+09:00",
      "title": "11月7日(金) 　青物１本勝負でした‼️",
      "entry_id": "12943909558"
    },
    {
      "url": "https://ameblo.jp/go-arimotomaru/entry-12943504596.html",
      "posted_at": "2025-11-06T05:43:38+09:00",
      "title": "11月5日(水)　今日も大型青物好調でした❗",
      "entry_id": "12943504596"
    },
    {
      "url": "https://ameblo.jp/go-arimotomaru/entry-12943095185.html",
      "posted_at": "2025-11-04T14:37:59+09:00",
      "title": "11月4日(火)　ブリワラサ34匹‼️マダイもいい食い‼️",
      "entry_id": "12943095185"
    },
    {
      "url": "https://ameblo.jp/go-arimotomaru/entry-12942773757.html",
      "posted_at": "2025-11-02T17:38:10+09:00",
      "title": "11月2日(日)　タチウオ好調でした‼️",
      "entry_id": "12942773757"
    },
    {
      "url": "https://ameblo.jp/go-arimotomaru/entry-12942245708.html",
      "posted_at": "2025-10-31T15:10:54+09:00",
      "title": "10月31日(金)　今日は青物ハマれずでした‼️",
      "entry_id": "12942245708"
    },
    {
      "url": "https://ameblo.jp/go-arimotomaru/entry-12942123653.html",
      "posted_at": "2025-10-30T17:12:05+09:00",
      "title": "10月30日(木)　今日もワラサ‼️タチウオ絶好調‼️",
      "entry_id": "12942123653"
    },
    {
      "url": "https://ameblo.jp/go-arimotomaru/entry-12941905752.html",
      "posted_at": "2025-10-29T15:18:22+09:00",
      "title": "10月29日(水)　ワラサいい感じです‼️",
      "entry_id": "12941905752"
    },
    {
      "url": "https://ameblo.jp/go-arimotomaru/entry-12941682694.html",
      "posted_at": "2025-10-28T17:10:10+09:00",
      "title": "10月28日(火)　なんとかワラサ‼️",
      "entry_id": "12941682694"
    },
    {
      "url": "https://ameblo.jp/go-arimotomaru/entry-12941094685.html",
      "posted_at": "2025-10-26T16:28:21+09:00",
      "title": "10月26日(日)　ブリワラサハマチサワラ‼️",
      "entry_id": "12941094685"
    },
    {
      "url": "https://ameblo.jp/go-arimotomaru/entry-12940936744.html",
      "posted_at": "2025-10-25T15:51:47+09:00",
      "title": "10月25日(土)　チャーター便でした❗",
      "entry_id": "12940936744"
    },
    {
      "url": "https://ameblo.jp/go-arimotomaru/entry-12940739219.html",
      "posted_at": "2025-10-24T16:45:41+09:00",
      "title": "10月24日(金)　今日もブリ‼️ワラサ‼️",
      "entry_id": "12940739219"
    },
    {
      "url": "https://ameblo.jp/go-arimotomaru/entry-12940482963.html",
      "posted_at": "2025-10-23T17:53:35+09:00",
      "title": "10月23日(木)　ブリ‼️ワラサ❗シーバスもっ‼️",
      "entry_id": "12940482963"
    },
    {
      "url": "https://ameblo.jp/go-arimotomaru/entry-12940051006.html",
      "posted_at": "2025-10-22T14:30:17+09:00",
      "title": "10月22日(水)　雨で寒かったですね‼️",
      "entry_id": "12940051006"
    },
    {
      "url": "https://ameblo.jp/go-arimotomaru/entry-12939932047.html",
      "posted_at": "2025-10-21T16:01:58+09:00",
      "title": "10月21日(火)　ブリキャッチでした‼️",
      "entry_id": "12939932047"
    },
    {
      "url": "https://ameblo.jp/go-arimotomaru/entry-12939696554.html",
      "posted_at": "2025-10-20T14:31:51+09:00",
      "title": "10月20日(月)　タチウオ入れ食い‼️カンパチマダイ‼️",
      "entry_id": "12939696554"
    },
    {
      "url": "https://ameblo.jp/go-arimotomaru/entry-12939487280.html",
      "posted_at": "2025-10-19T17:05:42+09:00",
      "title": "10月19日(日)　ワラサにドラゴンタチウオ⤴️",
      "entry_id": "12939487280"
    },
    {
      "url": "https://ameblo.jp/go-arimotomaru/entry-12939347565.html",
      "posted_at": "2025-10-18T17:32:01+09:00",
      "title": "10月18日(土)　青物気配出て来ました‼️",
      "entry_id": "12939347565"
    },
    {
      "url": "https://ameblo.jp/go-arimotomaru/entry-12939168925.html",
      "posted_at": "2025-10-17T17:57:32+09:00",
      "title": "10月17日(金)　良く釣れました‼️",
      "entry_id": "12939168925"
    },
    {
      "url": "https://ameblo.jp/go-arimotomaru/entry-12938806466.html",
      "posted_at": "2025-10-15T20:00:53+09:00",
      "title": "10月15日(水)　今日はボチボチいい感じ",
      "entry_id": "12938806466"
    },
    {
      "url": "https://ameblo.jp/go-arimotomaru/entry-12938479555.html",
      "posted_at": "2025-10-14T15:28:34+09:00",
      "title": "10月14日(火)　少し苦戦でしたが",
      "entry_id": "12938479555"
    },
    {
      "url": "https://ameblo.jp/go-arimotomaru/entry-12938279800.html",
      "posted_at": "2025-10-13T15:03:03+09:00",
      "title": "10月13日(月)　風ありましたがボチボチいい感じ‼️",
      "entry_id": "12938279800"
    },
    {
      "url": "https://ameblo.jp/go-arimotomaru/entry-12938153405.html",
      "posted_at": "2025-10-12T17:23:11+09:00",
      "title": "10月12日(日)　連日ボチボチいい感じ！",
      "entry_id": "12938153405"
    },
    {
      "url": "https://ameblo.jp/go-arimotomaru/entry-12937940338.html",
      "posted_at": "2025-10-11T14:26:33+09:00",
      "title": "10月11日(土)　今日もボチボチ釣れてます❗",
      "entry_id": "12937940338"
    },
    {
      "url": "https://ameblo.jp/go-arimotomaru/entry-12937808942.html",
      "posted_at": "2025-10-10T17:24:52+09:00",
      "title": "10月10日(金)　ボチボチでした‼️",
      "entry_id": "12937808942"
    },
    {
      "url": "https://ameblo.jp/go-arimotomaru/entry-12937324383.html",
      "posted_at": "2025-10-08T17:09:50+09:00",
      "title": "10月8日(水)　波高し❗",
      "entry_id": "12937324383"
    },
    {
      "url": "https://ameblo.jp/go-arimotomaru/entry-12936046711.html",
      "posted_at": "2025-10-05T14:35:25+09:00",
      "title": "10月5日(日)　良く釣れました～‼️",
      "entry_id": "12936046711"
    },
    {
      "url": "https://ameblo.jp/go-arimotomaru/entry-12935944482.html",
      "posted_at": "2025-10-04T17:43:39+09:00",
      "title": "10月４日(土)　雨の中！ハマチタチウオ！",
      "entry_id": "12935944482"
    },
    {
      "url": "https://ameblo.jp/go-arimotomaru/entry-12935358668.html",
      "posted_at": "2025-10-01T18:22:26+09:00",
      "title": "10月1日(水)　10月になりました‼️",
      "entry_id": "12935358668"
    },
    {
      "url": "https://ameblo.jp/go-arimotomaru/entry-12934967919.html",
      "posted_at": "2025-09-30T16:36:01+09:00",
      "title": "9月30日(火)　休みでした",
      "entry_id": "12934967919"
    },
    {
      "url": "https://ameblo.jp/go-arimotomaru/entry-12934315883.html",
      "posted_at": "2025-09-28T17:48:21+09:00",
      "title": "9月28日(日)　今日もマダイ好調でした⤴️",
      "entry_id": "12934315883"
    },
    {
      "url": "https://ameblo.jp/go-arimotomaru/entry-12933916861.html",
      "posted_at": "2025-09-27T14:28:48+09:00",
      "title": "9月27日(土)　今日もマダイいい感じ‼️",
      "entry_id": "12933916861"
    },
    {
      "url": "https://ameblo.jp/go-arimotomaru/entry-12933553004.html",
      "posted_at": "2025-09-26T18:30:02+09:00",
      "title": "9月26日(金)　マダイボコボコタイムあり‼️",
      "entry_id": "12933553004"
    },
    {
      "url": "https://ameblo.jp/go-arimotomaru/entry-12933340347.html",
      "posted_at": "2025-09-25T15:00:11+09:00",
      "title": "9月25日(木)　爆釣～の人もいた‼️",
      "entry_id": "12933340347"
    },
    {
      "url": "https://ameblo.jp/go-arimotomaru/entry-12932986337.html",
      "posted_at": "2025-09-24T15:39:06+09:00",
      "title": "9月24日(水)　今日も波高め！",
      "entry_id": "12932986337"
    },
    {
      "url": "https://ameblo.jp/go-arimotomaru/entry-12932614329.html",
      "posted_at": "2025-09-23T14:19:26+09:00",
      "title": "9月23日(火)　ボチボチいい感じでした⤴️",
      "entry_id": "12932614329"
    },
    {
      "url": "https://ameblo.jp/go-arimotomaru/entry-12932372186.html",
      "posted_at": "2025-09-22T18:04:39+09:00",
      "title": "9月22日(月)　タチウオ好調になってきました‼️",
      "entry_id": "12932372186"
    },
    {
      "url": "https://ameblo.jp/go-arimotomaru/entry-12931932743.html",
      "posted_at": "2025-09-21T17:02:44+09:00",
      "title": "9月21日(日)　タチウオデカい‼️",
      "entry_id": "12931932743"
    },
    {
      "url": "https://ameblo.jp/go-arimotomaru/entry-12931752166.html",
      "posted_at": "2025-09-20T18:11:28+09:00",
      "title": "9月20日(土)　雨パワー⁉️",
      "entry_id": "12931752166"
    },
    {
      "url": "https://ameblo.jp/go-arimotomaru/entry-12931388734.html",
      "posted_at": "2025-09-19T17:54:04+09:00",
      "title": "9月19日(金)　２日休んでの出船！",
      "entry_id": "12931388734"
    },
    {
      "url": "https://ameblo.jp/go-arimotomaru/entry-12930637349.html",
      "posted_at": "2025-09-16T15:31:44+09:00",
      "title": "9月16日(火)　カンパチに‼️タチウオ入れ食い‼️",
      "entry_id": "12930637349"
    },
    {
      "url": "https://ameblo.jp/go-arimotomaru/entry-12930291200.html",
      "posted_at": "2025-09-15T15:21:35+09:00",
      "title": "9月15日(月)　タチウオ入れ食い‼️マダムも大きい‼️",
      "entry_id": "12930291200"
    },
    {
      "url": "https://ameblo.jp/go-arimotomaru/entry-12930078365.html",
      "posted_at": "2025-09-14T13:58:51+09:00",
      "title": "9月14日(日)　青物‼️マダイ‼️タチウオ‼️",
      "entry_id": "12930078365"
    },
    {
      "url": "https://ameblo.jp/go-arimotomaru/entry-12929857888.html",
      "posted_at": "2025-09-13T13:36:42+09:00",
      "title": "9月13日(土)　久しぶりにエントリータチウオ",
      "entry_id": "12929857888"
    },
    {
      "url": "https://ameblo.jp/go-arimotomaru/entry-12929383923.html",
      "posted_at": "2025-09-11T15:17:56+09:00",
      "title": "9月11日(木)　マダイタイラバいい感じ",
      "entry_id": "12929383923"
    },
    {
      "url": "https://ameblo.jp/go-arimotomaru/entry-12929074800.html",
      "posted_at": "2025-09-10T15:49:23+09:00",
      "title": "9月10日(水)　良く釣れました⤴️",
      "entry_id": "12929074800"
    },
    {
      "url": "https://ameblo.jp/go-arimotomaru/entry-12928888413.html",
      "posted_at": "2025-09-09T15:23:40+09:00",
      "title": "9月9日(火)　今日もアレコレ良く釣れました",
      "entry_id": "12928888413"
    },
    {
      "url": "https://ameblo.jp/go-arimotomaru/entry-12928598632.html",
      "posted_at": "2025-09-08T14:29:51+09:00",
      "title": "9月8日(月)　今日もタイラバですね❗",
      "entry_id": "12928598632"
    },
    {
      "url": "https://ameblo.jp/go-arimotomaru/entry-12928395619.html",
      "posted_at": "2025-09-07T16:48:59+09:00",
      "title": "9月7日(日)　タイラバが面白い",
      "entry_id": "12928395619"
    },
    {
      "url": "https://ameblo.jp/go-arimotomaru/entry-12928126099.html",
      "posted_at": "2025-09-06T15:55:17+09:00",
      "title": "9月6日(土)　久しぶりの出船でした‼️",
      "entry_id": "12928126099"
    },
    {
      "url": "https://ameblo.jp/go-arimotomaru/entry-12926581992.html",
      "posted_at": "2025-08-31T18:05:32+09:00",
      "title": "8月31日(日)　今日もボチボチ釣れました‼️",
      "entry_id": "12926581992"
    },
    {
      "url": "https://ameblo.jp/go-arimotomaru/entry-12926362149.html",
      "posted_at": "2025-08-30T17:32:37+09:00",
      "title": "8月30日(土)　マダイいい感じ",
      "entry_id": "12926362149"
    },
    {
      "url": "https://ameblo.jp/go-arimotomaru/entry-12925715239.html",
      "posted_at": "2025-08-27T17:47:02+09:00",
      "title": "8月27日(水)　今日も少人数で頑張っていただきました‼️",
      "entry_id": "12925715239"
    },
    {
      "url": "https://ameblo.jp/go-arimotomaru/entry-12925250965.html",
      "posted_at": "2025-08-25T16:04:47+09:00",
      "title": "8月25日(月)　少人数で頑張っていただきました！",
      "entry_id": "12925250965"
    },
    {
      "url": "https://ameblo.jp/go-arimotomaru/entry-12924864802.html",
      "posted_at": "2025-08-24T15:31:40+09:00",
      "title": "8月24日(日)　今日も良く釣れます‼️",
      "entry_id": "12924864802"
    },
    {
      "url": "https://ameblo.jp/go-arimotomaru/entry-12924715762.html",
      "posted_at": "2025-08-23T14:39:22+09:00",
      "title": "8月23日(土)　今日もアレコレとたくさん",
      "entry_id": "12924715762"
    },
    {
      "url": "https://ameblo.jp/go-arimotomaru/entry-12924610585.html",
      "posted_at": "2025-08-22T16:38:46+09:00",
      "title": "8月22日(金)　今日も良く釣れました",
      "entry_id": "12924610585"
    },
    {
      "url": "https://ameblo.jp/go-arimotomaru/entry-12924197656.html",
      "posted_at": "2025-08-20T15:11:32+09:00",
      "title": "8月20日(水)　今日もたくさん釣れました‼️",
      "entry_id": "12924197656"
    },
    {
      "url": "https://ameblo.jp/go-arimotomaru/entry-12924039857.html",
      "posted_at": "2025-08-19T16:19:42+09:00",
      "title": "8月19日(火)　バイクの日",
      "entry_id": "12924039857"
    },
    {
      "url": "https://ameblo.jp/go-arimotomaru/entry-12923921580.html",
      "posted_at": "2025-08-18T17:19:26+09:00",
      "title": "8月18日(月)　お二人様で頑張って来ました！",
      "entry_id": "12923921580"
    },
    {
      "url": "https://ameblo.jp/go-arimotomaru/entry-12923648595.html",
      "posted_at": "2025-08-17T17:24:04+09:00",
      "title": "8月17日(日)　今日も１日アレコレ",
      "entry_id": "12923648595"
    },
    {
      "url": "https://ameblo.jp/go-arimotomaru/entry-12923389111.html",
      "posted_at": "2025-08-16T15:04:21+09:00",
      "title": "8月16日(土)　今日も１日ボチボチと‼️",
      "entry_id": "12923389111"
    },
    {
      "url": "https://ameblo.jp/go-arimotomaru/entry-12923201430.html",
      "posted_at": "2025-08-15T16:53:28+09:00",
      "title": "8月15日(金)　良く釣れました‼️",
      "entry_id": "12923201430"
    },
    {
      "url": "https://ameblo.jp/go-arimotomaru/entry-12922931332.html",
      "posted_at": "2025-08-14T17:10:40+09:00",
      "title": "８月14日(木)　なんやかんやと釣れる‼️",
      "entry_id": "12922931332"
    },
    {
      "url": "https://ameblo.jp/go-arimotomaru/entry-12922775639.html",
      "posted_at": "2025-08-13T19:46:14+09:00",
      "title": "８月13日(火)",
      "entry_id": "12922775639"
    },
    {
      "url": "https://ameblo.jp/go-arimotomaru/entry-12922524201.html",
      "posted_at": "2025-08-12T14:58:03+09:00",
      "title": "8月12日(火)　久しぶり出船",
      "entry_id": "12922524201"
    },
    {
      "url": "https://ameblo.jp/go-arimotomaru/entry-12921775932.html",
      "posted_at": "2025-08-09T16:40:26+09:00",
      "title": "8月9日(土)　ツバス！マダイ！タチウオ！",
      "entry_id": "12921775932"
    },
    {
      "url": "https://ameblo.jp/go-arimotomaru/entry-12921565545.html",
      "posted_at": "2025-08-08T17:36:21+09:00",
      "title": "8月8日(金)　今日もタチウオエントリー",
      "entry_id": "12921565545"
    },
    {
      "url": "https://ameblo.jp/go-arimotomaru/entry-12921210870.html",
      "posted_at": "2025-08-06T17:09:28+09:00",
      "title": "８月６日(水)　今日もエントリータチウオ‼️",
      "entry_id": "12921210870"
    },
    {
      "url": "https://ameblo.jp/go-arimotomaru/entry-12921003604.html",
      "posted_at": "2025-08-05T16:11:47+09:00",
      "title": "８月５日(火)　エントリータチウオとアレコレボチボチと‼️",
      "entry_id": "12921003604"
    },
    {
      "url": "https://ameblo.jp/go-arimotomaru/entry-12920767058.html",
      "posted_at": "2025-08-04T15:25:12+09:00",
      "title": "8月4日(月)　今日もエントリータチウオでました！",
      "entry_id": "12920767058"
    },
    {
      "url": "https://ameblo.jp/go-arimotomaru/entry-12920599722.html",
      "posted_at": "2025-08-03T17:56:38+09:00",
      "title": "８月３日(日)　エントリータチウオ❗",
      "entry_id": "12920599722"
    },
    {
      "url": "https://ameblo.jp/go-arimotomaru/entry-12920369446.html",
      "posted_at": "2025-08-02T17:30:01+09:00",
      "title": "８月２日(土)　マダイアジサバカマス",
      "entry_id": "12920369446"
    },
    {
      "url": "https://ameblo.jp/go-arimotomaru/entry-12920199964.html",
      "posted_at": "2025-08-01T17:27:35+09:00",
      "title": "８月１日(金)　伊勢湾ジギングバトルスタートです‼️",
      "entry_id": "12920199964"
    },
    {
      "url": "https://ameblo.jp/go-arimotomaru/entry-12919887840.html",
      "posted_at": "2025-07-31T17:43:40+09:00",
      "title": "7月31日(木)　今日はサバサバ‼️",
      "entry_id": "12919887840"
    },
    {
      "url": "https://ameblo.jp/go-arimotomaru/entry-12919477270.html",
      "posted_at": "2025-07-29T19:01:36+09:00",
      "title": "7月29日(火)　青物は残念",
      "entry_id": "12919477270"
    },
    {
      "url": "https://ameblo.jp/go-arimotomaru/entry-12919205799.html",
      "posted_at": "2025-07-28T16:19:53+09:00",
      "title": "7月28日(月)　今日もアレコレとです！",
      "entry_id": "12919205799"
    },
    {
      "url": "https://ameblo.jp/go-arimotomaru/entry-12919009157.html",
      "posted_at": "2025-07-27T16:09:47+09:00",
      "title": "7月27日(日)　マダイがよかった‼️",
      "entry_id": "12919009157"
    },
    {
      "url": "https://ameblo.jp/go-arimotomaru/entry-12918784676.html",
      "posted_at": "2025-07-26T15:40:47+09:00",
      "title": "7月26日(土)　ブリのジアイあり‼️",
      "entry_id": "12918784676"
    },
    {
      "url": "https://ameblo.jp/go-arimotomaru/entry-12918626277.html",
      "posted_at": "2025-07-25T18:09:58+09:00",
      "title": "7月25日(金)　ブリ！デカタチ！アジサバカマス！",
      "entry_id": "12918626277"
    },
    {
      "url": "https://ameblo.jp/go-arimotomaru/entry-12918354623.html",
      "posted_at": "2025-07-24T14:13:16+09:00",
      "title": "7月24日(木)　デカタチチャンス‼️",
      "entry_id": "12918354623"
    },
    {
      "url": "https://ameblo.jp/go-arimotomaru/entry-12918030308.html",
      "posted_at": "2025-07-22T17:11:37+09:00",
      "title": "7月22日(火)　今日もブリ！デカタチ‼️",
      "entry_id": "12918030308"
    },
    {
      "url": "https://ameblo.jp/go-arimotomaru/entry-12917846868.html",
      "posted_at": "2025-07-21T17:38:56+09:00",
      "title": "7月21日(月)　デカタチにブリにマダイに",
      "entry_id": "12917846868"
    },
    {
      "url": "https://ameblo.jp/go-arimotomaru/entry-12917682436.html",
      "posted_at": "2025-07-20T18:12:57+09:00",
      "title": "7月20日(日)　サバがデカい‼️",
      "entry_id": "12917682436"
    },
    {
      "url": "https://ameblo.jp/go-arimotomaru/entry-12917495856.html",
      "posted_at": "2025-07-19T20:31:10+09:00",
      "title": "7月19日(土)　久しぶりの出船‼️",
      "entry_id": "12917495856"
    },
    {
      "url": "https://ameblo.jp/go-arimotomaru/entry-12916480527.html",
      "posted_at": "2025-07-14T16:55:39+09:00",
      "title": "7月14日(月)　良く釣れました～",
      "entry_id": "12916480527"
    },
    {
      "url": "https://ameblo.jp/go-arimotomaru/entry-12916287455.html",
      "posted_at": "2025-07-13T18:10:50+09:00",
      "title": "7月13日(日)　チャーター便でした❗",
      "entry_id": "12916287455"
    },
    {
      "url": "https://ameblo.jp/go-arimotomaru/entry-12916108572.html",
      "posted_at": "2025-07-12T18:43:28+09:00",
      "title": "7月12日(土)　今日も好調です⤴️",
      "entry_id": "12916108572"
    },
    {
      "url": "https://ameblo.jp/go-arimotomaru/entry-12915923810.html",
      "posted_at": "2025-07-11T18:04:00+09:00",
      "title": "7月11日(金)　今日もいい感じです",
      "entry_id": "12915923810"
    },
    {
      "url": "https://ameblo.jp/go-arimotomaru/entry-12915677806.html",
      "posted_at": "2025-07-10T17:22:08+09:00",
      "title": "7月10日(木)　今日も好調です",
      "entry_id": "12915677806"
    },
    {
      "url": "https://ameblo.jp/go-arimotomaru/entry-12915463738.html",
      "posted_at": "2025-07-09T15:16:10+09:00",
      "title": "7月9日(水)　今日はマダイが良き",
      "entry_id": "12915463738"
    },
    {
      "url": "https://ameblo.jp/go-arimotomaru/entry-12915287430.html",
      "posted_at": "2025-07-08T14:27:52+09:00",
      "title": "7月8日(火)　暑いけどたくさん釣れました❗",
      "entry_id": "12915287430"
    },
    {
      "url": "https://ameblo.jp/go-arimotomaru/entry-12915042419.html",
      "posted_at": "2025-07-07T16:58:29+09:00",
      "title": "7月7日(月)　七夕ですね！",
      "entry_id": "12915042419"
    },
    {
      "url": "https://ameblo.jp/go-arimotomaru/entry-12914892406.html",
      "posted_at": "2025-07-06T18:46:23+09:00",
      "title": "7月6日(日)　サバダバサバダバ",
      "entry_id": "12914892406"
    },
    {
      "url": "https://ameblo.jp/go-arimotomaru/entry-12914692866.html",
      "posted_at": "2025-07-05T19:10:21+09:00",
      "title": "7月5日(土)　また海が変わってきてますね！",
      "entry_id": "12914692866"
    },
    {
      "url": "https://ameblo.jp/go-arimotomaru/entry-12914080547.html",
      "posted_at": "2025-07-02T14:26:34+09:00",
      "title": "7月2日(水)　今日はブリ！ハマチも！サバも！",
      "entry_id": "12914080547"
    },
    {
      "url": "https://ameblo.jp/go-arimotomaru/entry-12913895662.html",
      "posted_at": "2025-07-01T15:44:59+09:00",
      "title": "7月1日(火)　マダイ絶好調でした",
      "entry_id": "12913895662"
    },
    {
      "url": "https://ameblo.jp/go-arimotomaru/entry-12913710520.html",
      "posted_at": "2025-06-30T16:21:02+09:00",
      "title": "6月30日(月)　今日もブリゲットでした‼️",
      "entry_id": "12913710520"
    },
    {
      "url": "https://ameblo.jp/go-arimotomaru/entry-12913541071.html",
      "posted_at": "2025-06-29T18:23:25+09:00",
      "title": "6月29日(日)　岩田さんグループチャーター便",
      "entry_id": "12913541071"
    },
    {
      "url": "https://ameblo.jp/go-arimotomaru/entry-12913343789.html",
      "posted_at": "2025-06-28T18:22:54+09:00",
      "title": "6月28日(土)　今日はイマイチでした！",
      "entry_id": "12913343789"
    },
    {
      "url": "https://ameblo.jp/go-arimotomaru/entry-12913149515.html",
      "posted_at": "2025-06-27T19:00:06+09:00",
      "title": "6月27日(金)　今日はブリっ‼️",
      "entry_id": "12913149515"
    },
    {
      "url": "https://ameblo.jp/go-arimotomaru/entry-12912919972.html",
      "posted_at": "2025-06-26T15:52:13+09:00",
      "title": "6月26日(木)　ハヤブサ様撮影！タイラバ１本勝負‼️",
      "entry_id": "12912919972"
    },
    {
      "url": "https://ameblo.jp/go-arimotomaru/entry-12912916749.html",
      "posted_at": "2025-06-26T15:43:22+09:00",
      "title": "6月25日(水)　良く釣れました～❗",
      "entry_id": "12912916749"
    },
    {
      "url": "https://ameblo.jp/go-arimotomaru/entry-12912293178.html",
      "posted_at": "2025-06-23T20:04:44+09:00",
      "title": "6月23日(月)　今日もいい感じですね",
      "entry_id": "12912293178"
    },
    {
      "url": "https://ameblo.jp/go-arimotomaru/entry-12912083323.html",
      "posted_at": "2025-06-22T19:24:07+09:00",
      "title": "6月22日(日)　サワラがいいサイズ✨",
      "entry_id": "12912083323"
    },
    {
      "url": "https://ameblo.jp/go-arimotomaru/entry-12911893973.html",
      "posted_at": "2025-06-21T18:15:28+09:00",
      "title": "6月21日(土)　釣りガールブリ‼️",
      "entry_id": "12911893973"
    },
    {
      "url": "https://ameblo.jp/go-arimotomaru/entry-12911725202.html",
      "posted_at": "2025-06-20T19:25:34+09:00",
      "title": "6月20日(金)　いい感じにアレコレと‼️",
      "entry_id": "12911725202"
    },
    {
      "url": "https://ameblo.jp/go-arimotomaru/entry-12911466419.html",
      "posted_at": "2025-06-19T16:42:45+09:00",
      "title": "6月19日(木)　ハマチ良く釣れた‼️",
      "entry_id": "12911466419"
    },
    {
      "url": "https://ameblo.jp/go-arimotomaru/entry-12911303553.html",
      "posted_at": "2025-06-18T14:33:46+09:00",
      "title": "6月18日(水)　今日も好調です‼️",
      "entry_id": "12911303553"
    },
    {
      "url": "https://ameblo.jp/go-arimotomaru/entry-12910978033.html",
      "posted_at": "2025-06-16T19:08:18+09:00",
      "title": "6月16日(月)　今日も大漁～❗",
      "entry_id": "12910978033"
    },
    {
      "url": "https://ameblo.jp/go-arimotomaru/entry-12910760751.html",
      "posted_at": "2025-06-15T20:06:33+09:00",
      "title": "6月15日(日)　大漁でした‼️",
      "entry_id": "12910760751"
    },
    {
      "url": "https://ameblo.jp/go-arimotomaru/entry-12910431099.html",
      "posted_at": "2025-06-14T14:48:08+09:00",
      "title": "6月14日(土)　マダイ❗イロイロ釣れた‼️",
      "entry_id": "12910431099"
    },
    {
      "url": "https://ameblo.jp/go-arimotomaru/entry-12910307259.html",
      "posted_at": "2025-06-13T18:30:18+09:00",
      "title": "6月13日(金)　大きなマアジがっ",
      "entry_id": "12910307259"
    },
    {
      "url": "https://ameblo.jp/go-arimotomaru/entry-12910121949.html",
      "posted_at": "2025-06-12T18:39:26+09:00",
      "title": "6月12日(土)　サワラのジアイあり！",
      "entry_id": "12910121949"
    },
    {
      "url": "https://ameblo.jp/go-arimotomaru/entry-12909865464.html",
      "posted_at": "2025-06-11T16:49:46+09:00",
      "title": "6月11日(水)　雨パワー炸裂‼️",
      "entry_id": "12909865464"
    },
    {
      "url": "https://ameblo.jp/go-arimotomaru/entry-12909412625.html",
      "posted_at": "2025-06-09T17:42:20+09:00",
      "title": "6月9日(月)　今日もメーターザワラです‼️",
      "entry_id": "12909412625"
    },
    {
      "url": "https://ameblo.jp/go-arimotomaru/entry-12909227772.html",
      "posted_at": "2025-06-08T20:44:11+09:00",
      "title": "6月8日(日)　今日はボチボチです❗",
      "entry_id": "12909227772"
    },
    {
      "url": "https://ameblo.jp/go-arimotomaru/entry-12909014135.html",
      "posted_at": "2025-06-07T19:55:12+09:00",
      "title": "6月7日(土)　凪の週末❗",
      "entry_id": "12909014135"
    },
    {
      "url": "https://ameblo.jp/go-arimotomaru/entry-12908752725.html",
      "posted_at": "2025-06-06T18:27:27+09:00",
      "title": "６月６日(金)　今日もボチボチいい感じ",
      "entry_id": "12908752725"
    },
    {
      "url": "https://ameblo.jp/go-arimotomaru/entry-12908475874.html",
      "posted_at": "2025-06-05T13:46:47+09:00",
      "title": "６月５日(木)　今日もベイトは良い感じ❗",
      "entry_id": "12908475874"
    },
    {
      "url": "https://ameblo.jp/go-arimotomaru/entry-12908220451.html",
      "posted_at": "2025-06-04T18:46:49+09:00",
      "title": "６月４日(水)　今日もいいベイトです‼️",
      "entry_id": "12908220451"
    },
    {
      "url": "https://ameblo.jp/go-arimotomaru/entry-12907854116.html",
      "posted_at": "2025-06-02T18:46:34+09:00",
      "title": "6月２日(月)　青物よく釣れました‼️",
      "entry_id": "12907854116"
    },
    {
      "url": "https://ameblo.jp/go-arimotomaru/entry-12907369478.html",
      "posted_at": "2025-05-31T17:04:49+09:00",
      "title": "5月31日(土)　マダイはボチボチ❗",
      "entry_id": "12907369478"
    },
    {
      "url": "https://ameblo.jp/go-arimotomaru/entry-12907178071.html",
      "posted_at": "2025-05-30T21:15:28+09:00",
      "title": "5月30日(金)　今日は残念❗",
      "entry_id": "12907178071"
    },
    {
      "url": "https://ameblo.jp/go-arimotomaru/entry-12906951436.html",
      "posted_at": "2025-05-29T17:52:44+09:00",
      "title": "5月28日(木)　New「SSR」実釣会‼️",
      "entry_id": "12906951436"
    },
    {
      "url": "https://ameblo.jp/go-arimotomaru/entry-12906710434.html",
      "posted_at": "2025-05-28T17:08:59+09:00",
      "title": "5月28日(水)　今日はそれなりにっ‼️",
      "entry_id": "12906710434"
    },
    {
      "url": "https://ameblo.jp/go-arimotomaru/entry-12906443998.html",
      "posted_at": "2025-05-27T15:18:15+09:00",
      "title": "5月27日(火)　今日も好調です‼️‼️",
      "entry_id": "12906443998"
    },
    {
      "url": "https://ameblo.jp/go-arimotomaru/entry-12906075913.html",
      "posted_at": "2025-05-26T14:33:55+09:00",
      "title": "5月26日(月)　絶好調になってきました‼️",
      "entry_id": "12906075913"
    },
    {
      "url": "https://ameblo.jp/go-arimotomaru/entry-12905860852.html",
      "posted_at": "2025-05-25T15:44:26+09:00",
      "title": "5月25日(日)　今日もマダイ好調でした⤴️⤴️",
      "entry_id": "12905860852"
    },
    {
      "url": "https://ameblo.jp/go-arimotomaru/entry-12905552074.html",
      "posted_at": "2025-05-24T15:24:32+09:00",
      "title": "5月24日(土)　今日はいい感じでした⤴️",
      "entry_id": "12905552074"
    },
    {
      "url": "https://ameblo.jp/go-arimotomaru/entry-12905305399.html",
      "posted_at": "2025-05-23T14:53:29+09:00",
      "title": "5月23日(金)　久しぶりに出船‼️",
      "entry_id": "12905305399"
    },
    {
      "url": "https://ameblo.jp/go-arimotomaru/entry-12904278844.html",
      "posted_at": "2025-05-19T14:46:29+09:00",
      "title": "5月18日19日　マダイボチボチですね❗",
      "entry_id": "12904278844"
    }
  ]
}